pydrivedol/__init__.py
pydrivedol-0.0.2.dist-info/LICENSE
pydrivedol-0.0.2.dist-info/METADATA
pydrivedol-0.0.2.dist-info/WHEEL
pydrivedol-0.0.2.dist-info/top_level.txt
pydrivedol-0.0.2.dist-info/RECORD
