Metadata-Version: 2.1
Name: pydrivedol
Version: 0.0.2
Summary: pydrive (googledrive) with a simple (dict-like or list-like) interface
Home-page: https://github.com/i2mint/pydrivedol
Author: OtoSense
License: apache-2.0
Keywords: google drive,data
Platform: any
Requires-Dist: dol
Requires-Dist: pydrive
